lontra/__init__.py
lontra-0.0.1.dist-info/METADATA
lontra-0.0.1.dist-info/WHEEL
lontra-0.0.1.dist-info/RECORD
