Metadata-Version: 2.1
Name: lontra
Version: 0.0.1
Summary: 
Author: Sahand Nazarzadeh
Author-email: sahand.nazarzadeh@gmail.com
Requires-Python: >=3.10,<4.0
Classifier: Programming Language :: Python :: 3
Classifier: Programming Language :: Python :: 3.10
Classifier: Programming Language :: Python :: 3.11
Classifier: Programming Language :: Python :: 3.12
